{
  "schema_version": 2,
  "feed_tier": "advanced",
  "generated_at": "2026-04-07T16:36:38",
  "model_version": "AIM 2.0",
  "source": "aim_pocket_export",
  "tickers": [
    {
      "ticker": "NVDA",
      "company": "NVIDIA Corporation",
      "currency": "USD",
      "sector": "TECH",
      "price": 174.72999572753906,
      "fair_value": 178.8129226145754,
      "mos": 2.2833511288425914,
      "irr": 0.7729127803605351,
      "terminal_pe_irr": 10.850204058396585,
      "verdict": "BUY",
      "business_score_synt": 91.83416666666668,
      "investor_score_synt": 78.67162117661502,
      "market_score_synt": 79.3,
      "verdict_synt": "BUY",
      "confidence_synt": "High",
      "dps": null,
      "net_debt": -51516.0,
      "pe_now": 35.659182801538584,
      "analyst_pe_fwd_3y": 18.00790418353664,
      "market_cap_m": 4245938.896179199,
      "checklist_score": 84.06231513731268,
      "checklist_final": "BUY",
      "composite": {
        "score": 61.7,
        "rating": "Selective opportunity",
        "components": [
          {
            "key": "irr",
            "label": "IRR",
            "input": 10.85,
            "unit": "pct",
            "contribution": 21.7
          },
          {
            "key": "mos",
            "label": "MOS",
            "input": 2.34,
            "unit": "pct",
            "contribution": 15.0
          },
          {
            "key": "checklist",
            "label": "Checklist",
            "input": 84.06,
            "unit": "score",
            "contribution": 16.8
          },
          {
            "key": "quant",
            "label": "Quant",
            "input": 81.7,
            "unit": "score",
            "contribution": 8.2
          }
        ]
      },
      "market_valuation": {
        "score": 79.3,
        "rating": "OK",
        "signals": [
          {
            "key": "expectations_gap_pp",
            "label": "Expectations gap",
            "status": "GOOD",
            "value": -44.26,
            "unit": "pct",
            "message": "Current price reflects growth expectations well below analyst forecasts."
          },
          {
            "key": "pe_vs_hist_ratio",
            "label": "P/E regime",
            "status": "GOOD",
            "value": 0.69,
            "unit": "ratio",
            "message": "Current valuation sits below the company's historical P/E range."
          },
          {
            "key": "peg_ratio",
            "label": "PEG sanity",
            "status": "GOOD",
            "value": 0.92,
            "unit": "ratio",
            "message": "Valuation appears attractive relative to expected earnings growth."
          },
          {
            "key": "yield_sanity",
            "label": "FCF yield",
            "status": "OK",
            "value": 2.28,
            "unit": "pct",
            "message": "Free cash flow yield provides a modest valuation anchor."
          },
          {
            "key": "implied_irr_pct",
            "label": "Implied IRR",
            "status": "OK",
            "value": 10.85,
            "unit": "pct",
            "message": "Current price offers attractive IRR."
          }
        ]
      },
      "gqs": {
        "score": 61.1,
        "rating": "WARNING",
        "pillars": [
          {
            "key": "revenue",
            "label": "Revenue",
            "score": 50.0
          },
          {
            "key": "margin",
            "label": "Margin",
            "score": 66.7
          },
          {
            "key": "buybacks",
            "label": "Buybacks",
            "score": null
          },
          {
            "key": "roic",
            "label": "ROIC",
            "score": 66.7
          }
        ]
      },
      "pillar_scores": {
        "quality": 84.69047619047619,
        "profitability": 94.5,
        "capital_allocation": 96.65,
        "financial_health": 96.75
      },
      "valuation_state": "Attractive",
      "why": [
        "Revenue CAGR",
        "ROIC adj",
        "ROIC spread",
        "Gross margin",
        "Operating margin"
      ],
      "risks": [
        "Revenue volatility",
        "ROIC 5Y std",
        "Operating margin stability",
        "Operating margin stability 5Y",
        "EV / NOPAT"
      ],
      "meta": {
        "sector_mode": "TECH",
        "aim_verdict_score": 84.06231513731268,
        "confidence_score": 100.0,
        "confidence_label": "High",
        "freshness_label": "Fresh",
        "model_last_computed_at": "2026-04-07T16:35:29",
        "price_last_updated_at": "2026-04-07 16:35:25"
      }
    },
    {
      "ticker": "MSFT",
      "company": "Microsoft Corporation",
      "currency": "USD",
      "sector": "TECH",
      "price": 369.3699951171875,
      "fair_value": 409.2411720510892,
      "mos": 9.742709105750546,
      "irr": 3.4759054642294673,
      "terminal_pe_irr": 13.823496010652425,
      "verdict": "BUY",
      "business_score_synt": 91.26333333333335,
      "investor_score_synt": 78.57340667734829,
      "market_score_synt": 73.2,
      "verdict_synt": "BUY",
      "confidence_synt": "High",
      "dps": 3.2,
      "net_debt": -31855.0,
      "pe_now": 23.013706860883957,
      "analyst_pe_fwd_3y": 20.70813193332986,
      "market_cap_m": 2733337.9638671875,
      "checklist_score": 82.57469600427265,
      "checklist_final": "BUY",
      "composite": {
        "score": 75.8,
        "rating": "Selective opportunity",
        "components": [
          {
            "key": "irr",
            "label": "IRR",
            "input": 13.82,
            "unit": "pct",
            "contribution": 27.6
          },
          {
            "key": "mos",
            "label": "MOS",
            "input": 10.79,
            "unit": "pct",
            "contribution": 24.0
          },
          {
            "key": "checklist",
            "label": "Checklist",
            "input": 82.57,
            "unit": "score",
            "contribution": 16.5
          },
          {
            "key": "quant",
            "label": "Quant",
            "input": 76.29,
            "unit": "score",
            "contribution": 7.6
          }
        ]
      },
      "market_valuation": {
        "score": 73.2,
        "rating": "OK",
        "signals": [
          {
            "key": "expectations_gap_pp",
            "label": "Expectations gap",
            "status": "GOOD",
            "value": -12.08,
            "unit": "pct",
            "message": "Current price reflects growth expectations well below analyst forecasts."
          },
          {
            "key": "pe_vs_hist_ratio",
            "label": "P/E regime",
            "status": "GOOD",
            "value": 0.76,
            "unit": "ratio",
            "message": "Current valuation sits below the company's historical P/E range."
          },
          {
            "key": "peg_ratio",
            "label": "PEG sanity",
            "status": "WARNING",
            "value": 2.9,
            "unit": "ratio",
            "message": "Valuation appears stretched relative to expected earnings growth."
          },
          {
            "key": "yield_sanity",
            "label": "FCF yield",
            "status": "OK",
            "value": 2.83,
            "unit": "pct",
            "message": "Free cash flow yield provides a modest valuation anchor."
          },
          {
            "key": "implied_irr_pct",
            "label": "Implied IRR",
            "status": "OK",
            "value": 13.82,
            "unit": "pct",
            "message": "Current price offers attractive IRR."
          }
        ]
      },
      "gqs": {
        "score": 81.3,
        "rating": "OK",
        "pillars": [
          {
            "key": "revenue",
            "label": "Revenue",
            "score": 78.5
          },
          {
            "key": "margin",
            "label": "Margin",
            "score": 98.7
          },
          {
            "key": "buybacks",
            "label": "Buybacks",
            "score": null
          },
          {
            "key": "roic",
            "label": "ROIC",
            "score": 66.7
          }
        ]
      },
      "pillar_scores": {
        "quality": 93.1857142857143,
        "profitability": 97.0,
        "capital_allocation": 77.49166666666667,
        "financial_health": 93.66666666666667
      },
      "valuation_state": "Attractive",
      "why": [
        "ROIC spread",
        "ROIC 5Y avg",
        "Operating margin",
        "ROIC",
        "Operating margin stability 5Y"
      ],
      "risks": [
        "Growth efficiency",
        "CAPEX / Revenue",
        "PEG Ratio",
        "EV / NOPAT",
        "Price / Sales"
      ],
      "meta": {
        "sector_mode": "TECH",
        "aim_verdict_score": 82.57469600427265,
        "confidence_score": 100.0,
        "confidence_label": "High",
        "freshness_label": "Fresh",
        "model_last_computed_at": "2026-04-07T16:35:26",
        "price_last_updated_at": "2026-04-07 16:35:25"
      }
    },
    {
      "ticker": "META",
      "company": "Meta Platforms, Inc.",
      "currency": "USD",
      "sector": "TECH",
      "price": 569.2000122070312,
      "fair_value": 630.5033809166039,
      "mos": 9.722924660681743,
      "irr": 3.4683459114905,
      "terminal_pe_irr": 13.815180502639546,
      "verdict": "BUY",
      "business_score_synt": 89.33003623188408,
      "investor_score_synt": 77.23495817597836,
      "market_score_synt": 68.0,
      "verdict_synt": "BUY",
      "confidence_synt": "High",
      "dps": 2.1,
      "net_debt": 2305.0,
      "pe_now": 24.231588429418107,
      "analyst_pe_fwd_3y": 26.47863690911866,
      "market_cap_m": 1423000.0305175781,
      "checklist_score": 80.22599776314499,
      "checklist_final": "BUY",
      "composite": {
        "score": 73.7,
        "rating": "Selective opportunity",
        "components": [
          {
            "key": "irr",
            "label": "IRR",
            "input": 13.82,
            "unit": "pct",
            "contribution": 27.6
          },
          {
            "key": "mos",
            "label": "MOS",
            "input": 10.77,
            "unit": "pct",
            "contribution": 24.0
          },
          {
            "key": "checklist",
            "label": "Checklist",
            "input": 80.23,
            "unit": "score",
            "contribution": 16.0
          },
          {
            "key": "quant",
            "label": "Quant",
            "input": 60.72,
            "unit": "score",
            "contribution": 6.1
          }
        ]
      },
      "market_valuation": {
        "score": 68.0,
        "rating": "OK",
        "signals": [
          {
            "key": "expectations_gap_pp",
            "label": "Expectations gap",
            "status": "OK",
            "value": -4.4,
            "unit": "pct",
            "message": "Current price reflects growth expectations broadly in line with analyst forecasts."
          },
          {
            "key": "pe_vs_hist_ratio",
            "label": "P/E regime",
            "status": "OK",
            "value": 0.96,
            "unit": "ratio",
            "message": "Current valuation sits within the company's historical P/E range."
          },
          {
            "key": "peg_ratio",
            "label": "PEG sanity",
            "status": "WARNING",
            "value": 2.15,
            "unit": "ratio",
            "message": "Valuation appears stretched relative to expected earnings growth."
          },
          {
            "key": "yield_sanity",
            "label": "FCF yield",
            "status": "OK",
            "value": 3.24,
            "unit": "pct",
            "message": "Free cash flow yield provides a modest valuation anchor."
          },
          {
            "key": "implied_irr_pct",
            "label": "Implied IRR",
            "status": "OK",
            "value": 13.82,
            "unit": "pct",
            "message": "Current price offers attractive IRR."
          }
        ]
      },
      "gqs": {
        "score": 69.7,
        "rating": "WARNING",
        "pillars": [
          {
            "key": "revenue",
            "label": "Revenue",
            "score": 80.9
          },
          {
            "key": "margin",
            "label": "Margin",
            "score": 61.5
          },
          {
            "key": "buybacks",
            "label": "Buybacks",
            "score": null
          },
          {
            "key": "roic",
            "label": "ROIC",
            "score": 66.7
          }
        ]
      },
      "pillar_scores": {
        "quality": 92.70248447204969,
        "profitability": 93.91666666666667,
        "capital_allocation": 76.85833333333335,
        "financial_health": 88.91666666666666
      },
      "valuation_state": "Attractive",
      "why": [
        "ROIC 5Y avg",
        "Gross margin",
        "Operating margin",
        "Operating margin trend 3Y",
        "Incremental ROIC"
      ],
      "risks": [
        "Growth efficiency",
        "CAPEX / Revenue",
        "PEG Ratio",
        "EV / NOPAT",
        "Price / Sales"
      ],
      "meta": {
        "sector_mode": "TECH",
        "aim_verdict_score": 80.22599776314499,
        "confidence_score": 100.0,
        "confidence_label": "High",
        "freshness_label": "Fresh",
        "model_last_computed_at": "2026-04-07T16:35:35",
        "price_last_updated_at": "2026-04-07 16:35:25"
      }
    },
    {
      "ticker": "TSLA",
      "company": "Tesla, Inc.",
      "currency": "USD",
      "sector": "INDUSTRIAL",
      "price": 341.6199951171875,
      "fair_value": 257.0623591284748,
      "mos": -32.89382244658093,
      "irr": -9.043919875964235,
      "terminal_pe_irr": 0.05168813643934289,
      "verdict": "AVOID",
      "business_score_synt": 62.90723886328725,
      "investor_score_synt": 52.926415351488785,
      "market_score_synt": 32.400000000000006,
      "verdict_synt": "AVOID",
      "confidence_synt": "High",
      "dps": null,
      "net_debt": -35882.0,
      "pe_now": 316.3148102936921,
      "analyst_pe_fwd_3y": 128.4774007640817,
      "market_cap_m": 1205235.3427734375,
      "checklist_score": 45.81346168591042,
      "checklist_final": "AVOID",
      "composite": {
        "score": 15.3,
        "rating": "Weak risk/reward",
        "components": [
          {
            "key": "irr",
            "label": "IRR",
            "input": 0.05,
            "unit": "pct",
            "contribution": 0.1
          },
          {
            "key": "mos",
            "label": "MOS",
            "input": -24.75,
            "unit": "pct",
            "contribution": 0.0
          },
          {
            "key": "checklist",
            "label": "Checklist",
            "input": 45.81,
            "unit": "score",
            "contribution": 9.2
          },
          {
            "key": "quant",
            "label": "Quant",
            "input": 60.1,
            "unit": "score",
            "contribution": 6.0
          }
        ]
      },
      "market_valuation": {
        "score": 32.4,
        "rating": "BAD",
        "signals": [
          {
            "key": "expectations_gap_pp",
            "label": "Expectations gap",
            "status": "GOOD",
            "value": -21.95,
            "unit": "pct",
            "message": "Current price reflects growth expectations well below analyst forecasts."
          },
          {
            "key": "pe_vs_hist_ratio",
            "label": "P/E regime",
            "status": "BAD",
            "value": 1.6,
            "unit": "ratio",
            "message": "Current valuation sits well above the company's historical P/E range."
          },
          {
            "key": "peg_ratio",
            "label": "PEG sanity",
            "status": "BAD",
            "value": 8.21,
            "unit": "ratio",
            "message": "Valuation appears stretched relative to expected earnings growth."
          },
          {
            "key": "yield_sanity",
            "label": "FCF yield",
            "status": "BAD",
            "value": 0.52,
            "unit": "pct",
            "message": "Free cash flow yield provides limited valuation support."
          },
          {
            "key": "implied_irr_pct",
            "label": "Implied IRR",
            "status": "BAD",
            "value": 0.05,
            "unit": "pct",
            "message": "Current price offers very low IRR."
          }
        ]
      },
      "gqs": {
        "score": 48.2,
        "rating": "WEAK",
        "pillars": [
          {
            "key": "revenue",
            "label": "Revenue",
            "score": 38.0
          },
          {
            "key": "margin",
            "label": "Margin",
            "score": 27.9
          },
          {
            "key": "buybacks",
            "label": "Buybacks",
            "score": 60.3
          },
          {
            "key": "roic",
            "label": "ROIC",
            "score": 66.7
          }
        ]
      },
      "pillar_scores": {
        "quality": 56.51228878648233,
        "profitability": 39.0,
        "capital_allocation": 60.0,
        "financial_health": 91.91666666666667
      },
      "valuation_state": "Expensive",
      "why": [
        "Revenue CAGR",
        "ROIC 5Y avg",
        "Revenue persistence",
        "Operating margin stability 5Y",
        "CAPEX / Revenue"
      ],
      "risks": [
        "EBIT CAGR",
        "ROIC spread",
        "Revenue/EBIT divergence",
        "Operating margin",
        "Net margin"
      ],
      "meta": {
        "sector_mode": "INDUSTRIAL",
        "aim_verdict_score": 45.81346168591042,
        "confidence_score": 100.0,
        "confidence_label": "High",
        "freshness_label": "Fresh",
        "model_last_computed_at": "2026-04-07T16:35:58",
        "price_last_updated_at": "2026-04-07 16:35:25"
      }
    },
    {
      "ticker": "AMD",
      "company": "Advanced Micro Devices, Inc.",
      "currency": "USD",
      "sector": "TECH",
      "price": 218.0249938964844,
      "fair_value": 207.9263711495116,
      "mos": -4.8568263328711145,
      "irr": -1.5684258916313532,
      "terminal_pe_irr": 8.274731519205524,
      "verdict": "WATCHLIST",
      "business_score_synt": 75.49420289855074,
      "investor_score_synt": 66.18915545826157,
      "market_score_synt": 64.8,
      "verdict_synt": "WATCHLIST",
      "confidence_synt": "High",
      "dps": null,
      "net_debt": -6705.0,
      "pe_now": 82.27358260244695,
      "analyst_pe_fwd_3y": 30.1526142388936,
      "market_cap_m": 348839.99023437506,
      "checklist_score": 69.63334334272493,
      "checklist_final": "WATCHLIST",
      "composite": {
        "score": 48.6,
        "rating": "Neutral",
        "components": [
          {
            "key": "irr",
            "label": "IRR",
            "input": 8.27,
            "unit": "pct",
            "contribution": 16.5
          },
          {
            "key": "mos",
            "label": "MOS",
            "input": -4.63,
            "unit": "pct",
            "contribution": 10.5
          },
          {
            "key": "checklist",
            "label": "Checklist",
            "input": 69.63,
            "unit": "score",
            "contribution": 13.9
          },
          {
            "key": "quant",
            "label": "Quant",
            "input": 76.55,
            "unit": "score",
            "contribution": 7.7
          }
        ]
      },
      "market_valuation": {
        "score": 64.8,
        "rating": "OK",
        "signals": [
          {
            "key": "expectations_gap_pp",
            "label": "Expectations gap",
            "status": "GOOD",
            "value": -43.25,
            "unit": "pct",
            "message": "Current price reflects growth expectations well below analyst forecasts."
          },
          {
            "key": "pe_vs_hist_ratio",
            "label": "P/E regime",
            "status": "OK",
            "value": 1.01,
            "unit": "ratio",
            "message": "Current valuation sits within the company's historical P/E range."
          },
          {
            "key": "peg_ratio",
            "label": "PEG sanity",
            "status": "OK",
            "value": 1.52,
            "unit": "ratio",
            "message": "Valuation appears broadly aligned with expected earnings growth."
          },
          {
            "key": "yield_sanity",
            "label": "FCF yield",
            "status": "WARNING",
            "value": 1.92,
            "unit": "pct",
            "message": "Free cash flow yield provides limited valuation support."
          },
          {
            "key": "implied_irr_pct",
            "label": "Implied IRR",
            "status": "WARNING",
            "value": 8.27,
            "unit": "pct",
            "message": "Current price offers acceptable IRR."
          }
        ]
      },
      "gqs": {
        "score": 39.3,
        "rating": "WEAK",
        "pillars": [
          {
            "key": "revenue",
            "label": "Revenue",
            "score": 50.0
          },
          {
            "key": "margin",
            "label": "Margin",
            "score": 1.3
          },
          {
            "key": "buybacks",
            "label": "Buybacks",
            "score": null
          },
          {
            "key": "roic",
            "label": "ROIC",
            "score": 66.7
          }
        ]
      },
      "pillar_scores": {
        "quality": 70.1024844720497,
        "profitability": 69.0,
        "capital_allocation": 78.54166666666667,
        "financial_health": 97.0
      },
      "valuation_state": "Near Target",
      "why": [
        "Revenue CAGR",
        "ROIC 5Y avg",
        "Gross margin stability",
        "Operating margin trend 3Y",
        "Incremental ROIC"
      ],
      "risks": [
        "ROIC 5Y std",
        "Operating margin",
        "ROE",
        "ROIC spread",
        "Growth efficiency"
      ],
      "meta": {
        "sector_mode": "TECH",
        "aim_verdict_score": 69.63334334272493,
        "confidence_score": 100.0,
        "confidence_label": "High",
        "freshness_label": "Fresh",
        "model_last_computed_at": "2026-04-07T16:35:32",
        "price_last_updated_at": "2026-04-07 16:35:25"
      }
    },
    {
      "ticker": "AAPL",
      "company": "Apple Inc.",
      "currency": "USD",
      "sector": "TECH",
      "price": 247.60009765625,
      "fair_value": 204.16979714500368,
      "mos": -21.271657766501882,
      "irr": -6.226477837747668,
      "terminal_pe_irr": 3.150874378477586,
      "verdict": "WATCHLIST",
      "business_score_synt": 87.53750000000001,
      "investor_score_synt": 62.73656650092735,
      "market_score_synt": 36.0,
      "verdict_synt": "WATCHLIST",
      "confidence_synt": "High",
      "dps": 1.0,
      "net_debt": 43960.0,
      "pe_now": 31.421332189879443,
      "analyst_pe_fwd_3y": 24.81137035742082,
      "market_cap_m": 3639721.435546875,
      "checklist_score": 67.30962660037095,
      "checklist_final": "WATCHLIST",
      "composite": {
        "score": 24.2,
        "rating": "Weak risk/reward",
        "components": [
          {
            "key": "irr",
            "label": "IRR",
            "input": 3.15,
            "unit": "pct",
            "contribution": 6.3
          },
          {
            "key": "mos",
            "label": "MOS",
            "input": -17.54,
            "unit": "pct",
            "contribution": 0.0
          },
          {
            "key": "checklist",
            "label": "Checklist",
            "input": 67.31,
            "unit": "score",
            "contribution": 13.5
          },
          {
            "key": "quant",
            "label": "Quant",
            "input": 44.86,
            "unit": "score",
            "contribution": 4.5
          }
        ]
      },
      "market_valuation": {
        "score": 36.0,
        "rating": "BAD",
        "signals": [
          {
            "key": "expectations_gap_pp",
            "label": "Expectations gap",
            "status": "WARNING",
            "value": 6.43,
            "unit": "pct",
            "message": "Current price reflects growth expectations above analyst forecasts."
          },
          {
            "key": "pe_vs_hist_ratio",
            "label": "P/E regime",
            "status": "WARNING",
            "value": 1.16,
            "unit": "ratio",
            "message": "Current valuation sits above the company's historical P/E range."
          },
          {
            "key": "peg_ratio",
            "label": "PEG sanity",
            "status": "BAD",
            "value": 3.67,
            "unit": "ratio",
            "message": "Valuation appears stretched relative to expected earnings growth."
          },
          {
            "key": "yield_sanity",
            "label": "FCF yield",
            "status": "OK",
            "value": 2.71,
            "unit": "pct",
            "message": "Free cash flow yield provides a modest valuation anchor."
          },
          {
            "key": "implied_irr_pct",
            "label": "Implied IRR",
            "status": "BAD",
            "value": 3.15,
            "unit": "pct",
            "message": "Current price offers very low IRR."
          }
        ]
      },
      "gqs": {
        "score": 83.0,
        "rating": "OK",
        "pillars": [
          {
            "key": "revenue",
            "label": "Revenue",
            "score": 58.2
          },
          {
            "key": "margin",
            "label": "Margin",
            "score": 90.7
          },
          {
            "key": "buybacks",
            "label": "Buybacks",
            "score": null
          },
          {
            "key": "roic",
            "label": "ROIC",
            "score": 100.0
          }
        ]
      },
      "pillar_scores": {
        "quality": 84.69999999999999,
        "profitability": 93.875,
        "capital_allocation": 89.9,
        "financial_health": 78.33333333333334
      },
      "valuation_state": "Expensive",
      "why": [
        "ROIC adj",
        "ROIC spread",
        "ROIC 5Y avg",
        "ROIC",
        "Operating margin stability 5Y"
      ],
      "risks": [
        "Growth efficiency",
        "Working capital / Revenue",
        "Working capital",
        "PEG Ratio",
        "EV / NOPAT"
      ],
      "meta": {
        "sector_mode": "TECH",
        "aim_verdict_score": 67.30962660037095,
        "confidence_score": 100.0,
        "confidence_label": "High",
        "freshness_label": "Fresh",
        "model_last_computed_at": "2026-04-07T16:35:52",
        "price_last_updated_at": "2026-04-07 16:35:25"
      }
    },
    {
      "ticker": "AMZN",
      "company": "Amazon.com, Inc.",
      "currency": "USD",
      "sector": "TECH",
      "price": 210.16000366210935,
      "fair_value": 191.77310293012764,
      "mos": -9.58784128276892,
      "irr": -3.0057752959050332,
      "terminal_pe_irr": 6.693647174504469,
      "verdict": "WATCHLIST",
      "business_score_synt": 68.5686775362319,
      "investor_score_synt": 68.70346291803212,
      "market_score_synt": 58.5,
      "verdict_synt": "WATCHLIST",
      "confidence_synt": "High",
      "dps": null,
      "net_debt": 29958.0,
      "pe_now": 29.311018641856254,
      "analyst_pe_fwd_3y": 21.83319062296151,
      "market_cap_m": 2248712.03918457,
      "checklist_score": 66.60885618170562,
      "checklist_final": "WATCHLIST",
      "composite": {
        "score": 38.9,
        "rating": "Weak risk/reward",
        "components": [
          {
            "key": "irr",
            "label": "IRR",
            "input": 6.69,
            "unit": "pct",
            "contribution": 13.4
          },
          {
            "key": "mos",
            "label": "MOS",
            "input": -8.75,
            "unit": "pct",
            "contribution": 6.0
          },
          {
            "key": "checklist",
            "label": "Checklist",
            "input": 66.61,
            "unit": "score",
            "contribution": 13.3
          },
          {
            "key": "quant",
            "label": "Quant",
            "input": 61.71,
            "unit": "score",
            "contribution": 6.2
          }
        ]
      },
      "market_valuation": {
        "score": 58.5,
        "rating": "WARNING",
        "signals": [
          {
            "key": "expectations_gap_pp",
            "label": "Expectations gap",
            "status": "GOOD",
            "value": -30.01,
            "unit": "pct",
            "message": "Current price reflects growth expectations well below analyst forecasts."
          },
          {
            "key": "pe_vs_hist_ratio",
            "label": "P/E regime",
            "status": "GOOD",
            "value": 0.63,
            "unit": "ratio",
            "message": "Current valuation sits below the company's historical P/E range."
          },
          {
            "key": "peg_ratio",
            "label": "PEG sanity",
            "status": "OK",
            "value": 1.31,
            "unit": "ratio",
            "message": "Valuation appears broadly aligned with expected earnings growth."
          },
          {
            "key": "yield_sanity",
            "label": "FCF yield",
            "status": "BAD",
            "value": 0.34,
            "unit": "pct",
            "message": "Free cash flow yield provides limited valuation support."
          },
          {
            "key": "implied_irr_pct",
            "label": "Implied IRR",
            "status": "BAD",
            "value": 6.69,
            "unit": "pct",
            "message": "Current price offers weak IRR."
          }
        ]
      },
      "gqs": {
        "score": 57.2,
        "rating": "WEAK",
        "pillars": [
          {
            "key": "revenue",
            "label": "Revenue",
            "score": 77.9
          },
          {
            "key": "margin",
            "label": "Margin",
            "score": 61.7
          },
          {
            "key": "buybacks",
            "label": "Buybacks",
            "score": null
          },
          {
            "key": "roic",
            "label": "ROIC",
            "score": 32.0
          }
        ]
      },
      "pillar_scores": {
        "quality": 72.48788819875777,
        "profitability": 69.0,
        "capital_allocation": 59.95833333333333,
        "financial_health": 70.04166666666666
      },
      "valuation_state": "Expensive",
      "why": [
        "Revenue CAGR",
        "Gross margin",
        "Revenue persistence",
        "Operating margin trend 3Y",
        "Operating margin stability 5Y"
      ],
      "risks": [
        "Revenue/EBIT divergence",
        "Operating margin",
        "NOPAT margin",
        "ROIC spread",
        "Growth efficiency"
      ],
      "meta": {
        "sector_mode": "TECH",
        "aim_verdict_score": 66.60885618170562,
        "confidence_score": 100.0,
        "confidence_label": "High",
        "freshness_label": "Fresh",
        "model_last_computed_at": "2026-04-07T16:35:31",
        "price_last_updated_at": "2026-04-07 16:35:25"
      }
    },
    {
      "ticker": "AVGO",
      "company": "Broadcom Inc.",
      "currency": "USD",
      "sector": "TECH",
      "price": 323.5599975585937,
      "fair_value": 342.9752066115702,
      "mos": 5.660819988940132,
      "irr": 1.9614417061813771,
      "terminal_pe_irr": 12.157585876799537,
      "verdict": "BUY",
      "business_score_synt": 85.57937500000001,
      "investor_score_synt": 73.34026836427178,
      "market_score_synt": 68.2,
      "verdict_synt": "BUY",
      "confidence_synt": "High",
      "dps": 2.42,
      "net_debt": 50283.0,
      "pe_now": 63.07212428042762,
      "analyst_pe_fwd_3y": 27.67351620930658,
      "market_cap_m": 1524614.7084960935,
      "checklist_score": 77.20785734570872,
      "checklist_final": "BUY",
      "composite": {
        "score": 67.7,
        "rating": "Selective opportunity",
        "components": [
          {
            "key": "irr",
            "label": "IRR",
            "input": 12.16,
            "unit": "pct",
            "contribution": 24.3
          },
          {
            "key": "mos",
            "label": "MOS",
            "input": 6.0,
            "unit": "pct",
            "contribution": 19.5
          },
          {
            "key": "checklist",
            "label": "Checklist",
            "input": 77.21,
            "unit": "score",
            "contribution": 15.4
          },
          {
            "key": "quant",
            "label": "Quant",
            "input": 84.32,
            "unit": "score",
            "contribution": 8.4
          }
        ]
      },
      "market_valuation": {
        "score": 68.2,
        "rating": "OK",
        "signals": [
          {
            "key": "expectations_gap_pp",
            "label": "Expectations gap",
            "status": "GOOD",
            "value": -38.77,
            "unit": "pct",
            "message": "Current price reflects growth expectations well below analyst forecasts."
          },
          {
            "key": "pe_vs_hist_ratio",
            "label": "P/E regime",
            "status": "BAD",
            "value": 1.86,
            "unit": "ratio",
            "message": "Current valuation sits well above the company's historical P/E range."
          },
          {
            "key": "peg_ratio",
            "label": "PEG sanity",
            "status": "GOOD",
            "value": 1.05,
            "unit": "ratio",
            "message": "Valuation appears attractive relative to expected earnings growth."
          },
          {
            "key": "yield_sanity",
            "label": "FCF yield",
            "status": "WARNING",
            "value": 1.77,
            "unit": "pct",
            "message": "Free cash flow yield provides limited valuation support."
          },
          {
            "key": "implied_irr_pct",
            "label": "Implied IRR",
            "status": "OK",
            "value": 12.16,
            "unit": "pct",
            "message": "Current price offers attractive IRR."
          }
        ]
      },
      "gqs": {
        "score": 69.8,
        "rating": "WARNING",
        "pillars": [
          {
            "key": "revenue",
            "label": "Revenue",
            "score": 75.4
          },
          {
            "key": "margin",
            "label": "Margin",
            "score": 66.7
          },
          {
            "key": "buybacks",
            "label": "Buybacks",
            "score": 85.4
          },
          {
            "key": "roic",
            "label": "ROIC",
            "score": 52.0
          }
        ]
      },
      "pillar_scores": {
        "quality": 91.04285714285713,
        "profitability": 88.66666666666667,
        "capital_allocation": 76.025,
        "financial_health": 79.39583333333333
      },
      "valuation_state": "Attractive",
      "why": [
        "Revenue CAGR",
        "Operating margin",
        "Gross margin",
        "ROIC",
        "R&D / Revenue"
      ],
      "risks": [
        "Revenue volatility",
        "Growth efficiency",
        "Capital turnover",
        "Reinvestment rate",
        "Balance sheet flexibility"
      ],
      "meta": {
        "sector_mode": "TECH",
        "aim_verdict_score": 77.20785734570872,
        "confidence_score": 100.0,
        "confidence_label": "High",
        "freshness_label": "Fresh",
        "model_last_computed_at": "2026-04-07T16:35:54",
        "price_last_updated_at": "2026-04-07 16:35:25"
      }
    },
    {
      "ticker": "ASML.AS",
      "company": "ASML Holding N.V.",
      "currency": "EUR",
      "sector": "TECH",
      "price": 1108.5999755859375,
      "fair_value": 967.317806160781,
      "mos": -14.605558641155996,
      "irr": -4.44250144924454,
      "terminal_pe_irr": 5.113248405831006,
      "verdict": "BUY",
      "business_score_synt": 93.21336956521739,
      "investor_score_synt": 67.82064885025059,
      "market_score_synt": 56.0,
      "verdict_synt": "BUY",
      "confidence_synt": "High",
      "dps": 7.5,
      "net_debt": -10612.9,
      "pe_now": 43.74901245406225,
      "analyst_pe_fwd_3y": 27.70743823192818,
      "market_cap_m": 431245.3905029297,
      "checklist_score": 75.6136073661872,
      "checklist_final": "BUY",
      "composite": {
        "score": 32.0,
        "rating": "Weak risk/reward",
        "components": [
          {
            "key": "irr",
            "label": "IRR",
            "input": 5.11,
            "unit": "pct",
            "contribution": 10.2
          },
          {
            "key": "mos",
            "label": "MOS",
            "input": -12.74,
            "unit": "pct",
            "contribution": 0.0
          },
          {
            "key": "checklist",
            "label": "Checklist",
            "input": 75.61,
            "unit": "score",
            "contribution": 15.1
          },
          {
            "key": "quant",
            "label": "Quant",
            "input": 66.07,
            "unit": "score",
            "contribution": 6.6
          }
        ]
      },
      "market_valuation": {
        "score": 56.0,
        "rating": "WARNING",
        "signals": [
          {
            "key": "expectations_gap_pp",
            "label": "Expectations gap",
            "status": "OK",
            "value": -2.21,
            "unit": "pct",
            "message": "Current price reflects growth expectations broadly in line with analyst forecasts."
          },
          {
            "key": "pe_vs_hist_ratio",
            "label": "P/E regime",
            "status": "WARNING",
            "value": 1.24,
            "unit": "ratio",
            "message": "Current valuation sits above the company's historical P/E range."
          },
          {
            "key": "peg_ratio",
            "label": "PEG sanity",
            "status": "OK",
            "value": 1.8,
            "unit": "ratio",
            "message": "Valuation appears broadly aligned with expected earnings growth."
          },
          {
            "key": "yield_sanity",
            "label": "FCF yield",
            "status": "OK",
            "value": 2.57,
            "unit": "pct",
            "message": "Free cash flow yield provides a modest valuation anchor."
          },
          {
            "key": "implied_irr_pct",
            "label": "Implied IRR",
            "status": "BAD",
            "value": 5.11,
            "unit": "pct",
            "message": "Current price offers very low IRR."
          }
        ]
      },
      "gqs": {
        "score": 65.6,
        "rating": "WARNING",
        "pillars": [
          {
            "key": "revenue",
            "label": "Revenue",
            "score": 81.1
          },
          {
            "key": "margin",
            "label": "Margin",
            "score": 77.8
          },
          {
            "key": "buybacks",
            "label": "Buybacks",
            "score": 36.9
          },
          {
            "key": "roic",
            "label": "ROIC",
            "score": 66.7
          }
        ]
      },
      "pillar_scores": {
        "quality": 95.21677018633541,
        "profitability": 96.0,
        "capital_allocation": 84.0,
        "financial_health": 95.25
      },
      "valuation_state": "Expensive",
      "why": [
        "ROIC adj",
        "ROIC spread",
        "ROIC 5Y avg",
        "ROIC",
        "Operating margin stability 5Y"
      ],
      "risks": [
        "Growth efficiency",
        "Reinvestment rate",
        "EV / NOPAT",
        "Price / Sales"
      ],
      "meta": {
        "sector_mode": "TECH",
        "aim_verdict_score": 75.6136073661872,
        "confidence_score": 100.0,
        "confidence_label": "High",
        "freshness_label": "Fresh",
        "model_last_computed_at": "2026-04-07T16:36:22",
        "price_last_updated_at": "2026-04-07 16:35:25"
      }
    },
    {
      "ticker": "BAC",
      "company": "Bank of America Corporation",
      "currency": "USD",
      "sector": "FINANCIAL",
      "price": 50.095001220703125,
      "fair_value": 44.8534936138242,
      "mos": -11.68584024247211,
      "irr": -3.616958255928282,
      "terminal_pe_irr": 6.021345918478893,
      "verdict": "WATCHLIST",
      "business_score_synt": 72.18252351097179,
      "investor_score_synt": 66.42302871305728,
      "market_score_synt": 55.3,
      "verdict_synt": "WATCHLIST",
      "confidence_synt": "High",
      "dps": 1.08,
      "net_debt": 78497.0,
      "pe_now": 13.148294283649115,
      "analyst_pe_fwd_3y": 10.68844092723795,
      "market_cap_m": 384779.7043762207,
      "checklist_score": 66.50222088961164,
      "checklist_final": "WATCHLIST",
      "composite": {
        "score": 30.7,
        "rating": "Weak risk/reward",
        "components": [
          {
            "key": "irr",
            "label": "IRR",
            "input": 6.02,
            "unit": "pct",
            "contribution": 12.0
          },
          {
            "key": "mos",
            "label": "MOS",
            "input": -10.46,
            "unit": "pct",
            "contribution": 0.0
          },
          {
            "key": "checklist",
            "label": "Checklist",
            "input": 66.5,
            "unit": "score",
            "contribution": 13.3
          },
          {
            "key": "quant",
            "label": "Quant",
            "input": 53.8,
            "unit": "score",
            "contribution": 5.4
          }
        ]
      },
      "market_valuation": {
        "score": 55.3,
        "rating": "WARNING",
        "signals": [
          {
            "key": "expectations_gap_pp",
            "label": "Expectations gap",
            "status": "OK",
            "value": 3.06,
            "unit": "pct",
            "message": "Current price reflects growth expectations broadly in line with analyst forecasts."
          },
          {
            "key": "pe_vs_hist_ratio",
            "label": "P/E regime",
            "status": "OK",
            "value": 1.01,
            "unit": "ratio",
            "message": "Current valuation sits within the company's historical P/E range."
          },
          {
            "key": "peg_ratio",
            "label": "PEG sanity",
            "status": "N/A",
            "value": null,
            "unit": "ratio",
            "message": "Not applicable for FINANCE sector."
          },
          {
            "key": "yield_sanity",
            "label": "FCF yield",
            "status": "WARNING",
            "value": 3.28,
            "unit": "pct",
            "message": "Free cash flow yield provides limited valuation support."
          },
          {
            "key": "implied_irr_pct",
            "label": "Implied IRR",
            "status": "BAD",
            "value": 6.02,
            "unit": "pct",
            "message": "Current price offers weak IRR."
          }
        ]
      },
      "gqs": {
        "score": 55.8,
        "rating": "WEAK",
        "pillars": [
          {
            "key": "revenue",
            "label": "Revenue",
            "score": 58.7
          },
          {
            "key": "margin",
            "label": "Margin",
            "score": 100.0
          },
          {
            "key": "buybacks",
            "label": "Buybacks",
            "score": 23.3
          },
          {
            "key": "roic",
            "label": "ROIC",
            "score": 41.2
          }
        ]
      },
      "pillar_scores": {
        "quality": 76.13009404388715,
        "profitability": 69.0,
        "capital_allocation": 67.24999999999999,
        "financial_health": 74.54166666666667
      },
      "valuation_state": "Expensive",
      "why": [
        "NPL Ratio",
        "Capital Buffer",
        "CET1 Ratio",
        "NIM to NPL",
        "CET1 to NPL"
      ],
      "risks": [
        "Deposits / Loans Trend 3Y",
        "Deposit vs Loan Growth Spread 3Y",
        "NPL Trend 3Y",
        "NIM",
        "Cost / Income to NIM"
      ],
      "meta": {
        "sector_mode": "FINANCIAL",
        "aim_verdict_score": 66.50222088961164,
        "confidence_score": 100.0,
        "confidence_label": "High",
        "freshness_label": "Fresh",
        "model_last_computed_at": "2026-04-07T16:36:16",
        "price_last_updated_at": "2026-04-07 16:35:25"
      }
    },
    {
      "ticker": "COST",
      "company": "Costco Wholesale Corporation",
      "currency": "USD",
      "sector": "CONSUMER",
      "price": 1012.3350219726562,
      "fair_value": 776.2584522915098,
      "mos": -30.41210939272223,
      "irr": -8.470583558633137,
      "terminal_pe_irr": 0.6823580855035649,
      "verdict": "SPECULATIVE",
      "business_score_synt": 81.11869047619047,
      "investor_score_synt": 59.97645421962635,
      "market_score_synt": 23.0,
      "verdict_synt": "SPECULATIVE",
      "confidence_synt": "High",
      "dps": 4.9,
      "net_debt": -7111.0,
      "pe_now": 52.561527620594816,
      "analyst_pe_fwd_3y": 37.77714916695164,
      "market_cap_m": 449173.04924926755,
      "checklist_score": 61.03805787832673,
      "checklist_final": "SPECULATIVE",
      "composite": {
        "score": 17.7,
        "rating": "Weak risk/reward",
        "components": [
          {
            "key": "irr",
            "label": "IRR",
            "input": 0.68,
            "unit": "pct",
            "contribution": 1.4
          },
          {
            "key": "mos",
            "label": "MOS",
            "input": -23.32,
            "unit": "pct",
            "contribution": 0.0
          },
          {
            "key": "checklist",
            "label": "Checklist",
            "input": 61.04,
            "unit": "score",
            "contribution": 12.2
          },
          {
            "key": "quant",
            "label": "Quant",
            "input": 41.2,
            "unit": "score",
            "contribution": 4.1
          }
        ]
      },
      "market_valuation": {
        "score": 23.0,
        "rating": "BAD",
        "signals": [
          {
            "key": "expectations_gap_pp",
            "label": "Expectations gap",
            "status": "BAD",
            "value": 11.25,
            "unit": "pct",
            "message": "Current price reflects growth expectations above analyst forecasts."
          },
          {
            "key": "pe_vs_hist_ratio",
            "label": "P/E regime",
            "status": "WARNING",
            "value": 1.37,
            "unit": "ratio",
            "message": "Current valuation sits above the company's historical P/E range."
          },
          {
            "key": "peg_ratio",
            "label": "PEG sanity",
            "status": "BAD",
            "value": 4.75,
            "unit": "ratio",
            "message": "Valuation appears stretched relative to expected earnings growth."
          },
          {
            "key": "yield_sanity",
            "label": "FCF yield",
            "status": "WARNING",
            "value": 1.74,
            "unit": "pct",
            "message": "Free cash flow yield provides limited valuation support."
          },
          {
            "key": "implied_irr_pct",
            "label": "Implied IRR",
            "status": "BAD",
            "value": 0.68,
            "unit": "pct",
            "message": "Current price offers very low IRR."
          }
        ]
      },
      "gqs": {
        "score": 74.5,
        "rating": "WARNING",
        "pillars": [
          {
            "key": "revenue",
            "label": "Revenue",
            "score": 72.2
          },
          {
            "key": "margin",
            "label": "Margin",
            "score": 51.3
          },
          {
            "key": "buybacks",
            "label": "Buybacks",
            "score": null
          },
          {
            "key": "roic",
            "label": "ROIC",
            "score": 100.0
          }
        ]
      },
      "pillar_scores": {
        "quality": 84.49285714285713,
        "profitability": 69.0,
        "capital_allocation": 80.75,
        "financial_health": 91.66666666666666
      },
      "valuation_state": "Expensive",
      "why": [
        "ROIC adj",
        "ROIC spread",
        "ROIC 5Y avg",
        "ROIC",
        "Operating margin stability 5Y"
      ],
      "risks": [
        "Gross margin",
        "Operating margin",
        "Net margin",
        "Reinvestment rate",
        "CAPEX / Revenue"
      ],
      "meta": {
        "sector_mode": "CONSUMER",
        "aim_verdict_score": 61.03805787832673,
        "confidence_score": 100.0,
        "confidence_label": "High",
        "freshness_label": "Fresh",
        "model_last_computed_at": "2026-04-07T16:35:36",
        "price_last_updated_at": "2026-04-07 16:35:25"
      }
    },
    {
      "ticker": "CVX",
      "company": "Chevron Corporation",
      "currency": "USD",
      "sector": "ENERGY",
      "price": 203.82000732421875,
      "fair_value": 145.79263711495116,
      "mos": -39.80130365809593,
      "irr": -10.567317061048144,
      "terminal_pe_irr": -1.6240487671529524,
      "verdict": "SPECULATIVE",
      "business_score_synt": 69.0625,
      "investor_score_synt": 61.16533333333333,
      "market_score_synt": 40.6,
      "verdict_synt": "SPECULATIVE",
      "confidence_synt": "High",
      "dps": 6.84,
      "net_debt": 33802.0,
      "pe_now": 30.74208255267251,
      "analyst_pe_fwd_3y": 18.55842763243763,
      "market_cap_m": 378289.93359375,
      "checklist_score": 60.211133333333336,
      "checklist_final": "SPECULATIVE",
      "composite": {
        "score": 16.7,
        "rating": "Weak risk/reward",
        "components": [
          {
            "key": "irr",
            "label": "IRR",
            "input": -1.62,
            "unit": "pct",
            "contribution": 0.0
          },
          {
            "key": "mos",
            "label": "MOS",
            "input": -28.47,
            "unit": "pct",
            "contribution": 0.0
          },
          {
            "key": "checklist",
            "label": "Checklist",
            "input": 60.21,
            "unit": "score",
            "contribution": 12.0
          },
          {
            "key": "quant",
            "label": "Quant",
            "input": 46.24,
            "unit": "score",
            "contribution": 4.6
          }
        ]
      },
      "market_valuation": {
        "score": 40.6,
        "rating": "WARNING",
        "signals": [
          {
            "key": "expectations_gap_pp",
            "label": "Expectations gap",
            "status": "BAD",
            "value": 19.59,
            "unit": "pct",
            "message": "Current price reflects growth expectations above analyst forecasts."
          },
          {
            "key": "pe_vs_hist_ratio",
            "label": "P/E regime",
            "status": "BAD",
            "value": 2.13,
            "unit": "ratio",
            "message": "Current valuation sits well above the company's historical P/E range."
          },
          {
            "key": "peg_ratio",
            "label": "PEG sanity",
            "status": "OK",
            "value": 1.04,
            "unit": "ratio",
            "message": "Valuation appears broadly aligned with expected earnings growth."
          },
          {
            "key": "yield_sanity",
            "label": "FCF yield",
            "status": "OK",
            "value": 4.39,
            "unit": "pct",
            "message": "Free cash flow yield provides a modest valuation anchor."
          },
          {
            "key": "implied_irr_pct",
            "label": "Implied IRR",
            "status": "BAD",
            "value": -1.62,
            "unit": "pct",
            "message": "Current price implies negative IRR."
          }
        ]
      },
      "gqs": {
        "score": 31.2,
        "rating": "WEAK",
        "pillars": [
          {
            "key": "revenue",
            "label": "Revenue",
            "score": 10.9
          },
          {
            "key": "margin",
            "label": "Margin",
            "score": 46.5
          },
          {
            "key": "buybacks",
            "label": "Buybacks",
            "score": 41.6
          },
          {
            "key": "roic",
            "label": "ROIC",
            "score": 26.0
          }
        ]
      },
      "pillar_scores": {
        "quality": 77.66666666666666,
        "profitability": 66.25,
        "capital_allocation": 56.0,
        "financial_health": 76.0
      },
      "valuation_state": "Expensive",
      "why": [
        "ROIC 5Y avg",
        "Operating margin stability",
        "Revenue persistence",
        "Operating margin stability 5Y",
        "Net margin"
      ],
      "risks": [
        "ROIC spread",
        "Operating margin trend 3Y",
        "Reinvestment rate",
        "Growth efficiency (CAPEX-based)",
        "Balance sheet flexibility"
      ],
      "meta": {
        "sector_mode": "ENERGY",
        "aim_verdict_score": 60.211133333333336,
        "confidence_score": 100.0,
        "confidence_label": "High",
        "freshness_label": "Fresh",
        "model_last_computed_at": "2026-04-07T16:36:25",
        "price_last_updated_at": "2026-04-07 16:35:25"
      }
    },
    {
      "ticker": "GOOGL",
      "company": "Alphabet Inc.",
      "currency": "USD",
      "sector": "TECH",
      "price": 300.2850036621094,
      "fair_value": 229.52667167543188,
      "mos": -30.827934492395347,
      "irr": -8.567659217372404,
      "terminal_pe_irr": 0.575574860890371,
      "verdict": "WATCHLIST",
      "business_score_synt": 90.19083333333334,
      "investor_score_synt": 63.99293107401521,
      "market_score_synt": 61.2,
      "verdict_synt": "WATCHLIST",
      "confidence_synt": "High",
      "dps": 0.8,
      "net_debt": -67552.0,
      "pe_now": 27.804167005750866,
      "analyst_pe_fwd_3y": 19.70879898979172,
      "market_cap_m": 3633448.5443115234,
      "checklist_score": 73.91350576293942,
      "checklist_final": "WATCHLIST",
      "composite": {
        "score": 20.1,
        "rating": "Weak risk/reward",
        "components": [
          {
            "key": "irr",
            "label": "IRR",
            "input": 0.58,
            "unit": "pct",
            "contribution": 1.2
          },
          {
            "key": "mos",
            "label": "MOS",
            "input": -23.56,
            "unit": "pct",
            "contribution": 0.0
          },
          {
            "key": "checklist",
            "label": "Checklist",
            "input": 73.91,
            "unit": "score",
            "contribution": 14.8
          },
          {
            "key": "quant",
            "label": "Quant",
            "input": 41.63,
            "unit": "score",
            "contribution": 4.2
          }
        ]
      },
      "market_valuation": {
        "score": 61.2,
        "rating": "OK",
        "signals": [
          {
            "key": "expectations_gap_pp",
            "label": "Expectations gap",
            "status": "OK",
            "value": -3.51,
            "unit": "pct",
            "message": "Current price reflects growth expectations broadly in line with analyst forecasts."
          },
          {
            "key": "pe_vs_hist_ratio",
            "label": "P/E regime",
            "status": "OK",
            "value": 1.13,
            "unit": "ratio",
            "message": "Current valuation sits within the company's historical P/E range."
          },
          {
            "key": "peg_ratio",
            "label": "PEG sanity",
            "status": "OK",
            "value": 1.6,
            "unit": "ratio",
            "message": "Valuation appears broadly aligned with expected earnings growth."
          },
          {
            "key": "yield_sanity",
            "label": "FCF yield",
            "status": "OK",
            "value": 2.02,
            "unit": "pct",
            "message": "Free cash flow yield provides a modest valuation anchor."
          },
          {
            "key": "implied_irr_pct",
            "label": "Implied IRR",
            "status": "BAD",
            "value": 0.58,
            "unit": "pct",
            "message": "Current price offers very low IRR."
          }
        ]
      },
      "gqs": {
        "score": 78.1,
        "rating": "OK",
        "pillars": [
          {
            "key": "revenue",
            "label": "Revenue",
            "score": 79.6
          },
          {
            "key": "margin",
            "label": "Margin",
            "score": 88.0
          },
          {
            "key": "buybacks",
            "label": "Buybacks",
            "score": null
          },
          {
            "key": "roic",
            "label": "ROIC",
            "score": 66.7
          }
        ]
      },
      "pillar_scores": {
        "quality": 91.58571428571429,
        "profitability": 94.5,
        "capital_allocation": 79.36666666666667,
        "financial_health": 92.75
      },
      "valuation_state": "Expensive",
      "why": [
        "ROIC 5Y avg",
        "Operating margin",
        "ROIC adj",
        "ROIC",
        "Operating margin trend 3Y"
      ],
      "risks": [
        "Growth efficiency",
        "CAPEX / Revenue",
        "EV / NOPAT",
        "Price / Sales"
      ],
      "meta": {
        "sector_mode": "TECH",
        "aim_verdict_score": 73.91350576293942,
        "confidence_score": 100.0,
        "confidence_label": "High",
        "freshness_label": "Fresh",
        "model_last_computed_at": "2026-04-07T16:35:38",
        "price_last_updated_at": "2026-04-07 16:35:25"
      }
    },
    {
      "ticker": "INTC",
      "company": "Intel Corporation",
      "currency": "USD",
      "sector": "TECH",
      "price": 52.0,
      "fair_value": 31.123215627347847,
      "mos": -67.07785153892584,
      "irr": -15.725980957478436,
      "terminal_pe_irr": -7.298579053226273,
      "verdict": "AVOID",
      "business_score_synt": 26.16916666666667,
      "investor_score_synt": 33.50774074074074,
      "market_score_synt": 18.0,
      "verdict_synt": "AVOID",
      "confidence_synt": "High",
      "dps": 0.0,
      "net_debt": 9169.0,
      "pe_now": 123.80952380952381,
      "analyst_pe_fwd_3y": 50.37804356285957,
      "market_cap_m": 260000.0,
      "checklist_score": 20.470762962962965,
      "checklist_final": "AVOID",
      "composite": {
        "score": 10.1,
        "rating": "Weak risk/reward",
        "components": [
          {
            "key": "irr",
            "label": "IRR",
            "input": -7.3,
            "unit": "pct",
            "contribution": 0.0
          },
          {
            "key": "mos",
            "label": "MOS",
            "input": -40.15,
            "unit": "pct",
            "contribution": 0.0
          },
          {
            "key": "checklist",
            "label": "Checklist",
            "input": 20.47,
            "unit": "score",
            "contribution": 4.1
          },
          {
            "key": "quant",
            "label": "Quant",
            "input": 60.0,
            "unit": "score",
            "contribution": 6.0
          }
        ]
      },
      "market_valuation": {
        "score": 18.0,
        "rating": "BAD",
        "signals": [
          {
            "key": "expectations_gap_pp",
            "label": "Expectations gap",
            "status": "BAD",
            "value": 840.86,
            "unit": "pct",
            "message": "Current price reflects growth expectations above analyst forecasts."
          },
          {
            "key": "pe_vs_hist_ratio",
            "label": "P/E regime",
            "status": "BAD",
            "value": 735.29,
            "unit": "ratio",
            "message": "Current valuation sits well above the company's historical P/E range."
          },
          {
            "key": "peg_ratio",
            "label": "PEG sanity",
            "status": "N/A",
            "value": null,
            "unit": "ratio",
            "message": "PEG signal is not available."
          },
          {
            "key": "yield_sanity",
            "label": "Earnings yield",
            "status": "BAD",
            "value": 0.01,
            "unit": "pct",
            "message": "Earnings yield provides limited valuation support."
          },
          {
            "key": "implied_irr_pct",
            "label": "Implied IRR",
            "status": "BAD",
            "value": -7.3,
            "unit": "pct",
            "message": "Current price implies negative IRR."
          }
        ]
      },
      "gqs": {
        "score": 18.1,
        "rating": "WEAK",
        "pillars": [
          {
            "key": "revenue",
            "label": "Revenue",
            "score": 50.0
          },
          {
            "key": "margin",
            "label": "Margin",
            "score": 0.0
          },
          {
            "key": "buybacks",
            "label": "Buybacks",
            "score": null
          },
          {
            "key": "roic",
            "label": "ROIC",
            "score": 4.4
          }
        ]
      },
      "pillar_scores": {
        "quality": 20.064285714285713,
        "profitability": 23.75,
        "capital_allocation": 26.35833333333333,
        "financial_health": 45.0
      },
      "valuation_state": "Risky",
      "why": [
        "Revenue persistence",
        "Balance sheet flexibility",
        "Net debt / FCF",
        "Debt payback years"
      ],
      "risks": [
        "ROIC spread",
        "Revenue CAGR",
        "Operating margin",
        "ROIC",
        "Incremental ROIC"
      ],
      "meta": {
        "sector_mode": "TECH",
        "aim_verdict_score": 20.470762962962965,
        "confidence_score": 100.0,
        "confidence_label": "High",
        "freshness_label": "Fresh",
        "model_last_computed_at": "2026-04-07T16:35:34",
        "price_last_updated_at": "2026-04-07 16:35:25"
      }
    },
    {
      "ticker": "KO",
      "company": "The Coca-Cola Company",
      "currency": "USD",
      "sector": "CONSUMER",
      "price": 77.06999969482422,
      "fair_value": 59.99248685199096,
      "mos": -28.466085903332594,
      "irr": -8.010730676276234,
      "terminal_pe_irr": 1.1881962560961634,
      "verdict": "WATCHLIST",
      "business_score_synt": 81.25315476190477,
      "investor_score_synt": 62.31160630321294,
      "market_score_synt": 41.2,
      "verdict_synt": "WATCHLIST",
      "confidence_synt": "High",
      "dps": 2.04,
      "net_debt": 31408.0,
      "pe_now": 25.351973583823757,
      "analyst_pe_fwd_3y": 21.32146200515329,
      "market_cap_m": 331632.2086868286,
      "checklist_score": 65.66590442604709,
      "checklist_final": "WATCHLIST",
      "composite": {
        "score": 18.9,
        "rating": "Weak risk/reward",
        "components": [
          {
            "key": "irr",
            "label": "IRR",
            "input": 1.19,
            "unit": "pct",
            "contribution": 2.4
          },
          {
            "key": "mos",
            "label": "MOS",
            "input": -22.16,
            "unit": "pct",
            "contribution": 0.0
          },
          {
            "key": "checklist",
            "label": "Checklist",
            "input": 65.67,
            "unit": "score",
            "contribution": 13.1
          },
          {
            "key": "quant",
            "label": "Quant",
            "input": 33.9,
            "unit": "score",
            "contribution": 3.4
          }
        ]
      },
      "market_valuation": {
        "score": 41.2,
        "rating": "WARNING",
        "signals": [
          {
            "key": "expectations_gap_pp",
            "label": "Expectations gap",
            "status": "OK",
            "value": 0.24,
            "unit": "pct",
            "message": "Current price reflects growth expectations broadly in line with analyst forecasts."
          },
          {
            "key": "pe_vs_hist_ratio",
            "label": "P/E regime",
            "status": "OK",
            "value": 1.0,
            "unit": "ratio",
            "message": "Current valuation sits within the company's historical P/E range."
          },
          {
            "key": "peg_ratio",
            "label": "PEG sanity",
            "status": "BAD",
            "value": 2.36,
            "unit": "ratio",
            "message": "Valuation appears stretched relative to expected earnings growth."
          },
          {
            "key": "yield_sanity",
            "label": "FCF yield",
            "status": "WARNING",
            "value": 1.6,
            "unit": "pct",
            "message": "Free cash flow yield provides limited valuation support."
          },
          {
            "key": "implied_irr_pct",
            "label": "Implied IRR",
            "status": "BAD",
            "value": 1.19,
            "unit": "pct",
            "message": "Current price offers very low IRR."
          }
        ]
      },
      "gqs": {
        "score": 67.2,
        "rating": "WARNING",
        "pillars": [
          {
            "key": "revenue",
            "label": "Revenue",
            "score": 63.8
          },
          {
            "key": "margin",
            "label": "Margin",
            "score": 90.1
          },
          {
            "key": "buybacks",
            "label": "Buybacks",
            "score": 49.3
          },
          {
            "key": "roic",
            "label": "ROIC",
            "score": 65.7
          }
        ]
      },
      "pillar_scores": {
        "quality": 85.00357142857143,
        "profitability": 93.33333333333333,
        "capital_allocation": 76.125,
        "financial_health": 66.9375
      },
      "valuation_state": "Expensive",
      "why": [
        "Gross margin",
        "Operating margin",
        "ROIC adj",
        "Operating margin trend 3Y",
        "ROIC spread"
      ],
      "risks": [
        "Reinvestment rate",
        "Balance sheet flexibility",
        "FCF Yield"
      ],
      "meta": {
        "sector_mode": "CONSUMER",
        "aim_verdict_score": 65.66590442604709,
        "confidence_score": 100.0,
        "confidence_label": "High",
        "freshness_label": "Fresh",
        "model_last_computed_at": "2026-04-07T16:36:09",
        "price_last_updated_at": "2026-04-07 16:35:25"
      }
    },
    {
      "ticker": "NFLX",
      "company": "Netflix, Inc.",
      "currency": "USD",
      "sector": "TECH",
      "price": 98.95500183105467,
      "fair_value": 80.50338091660403,
      "mos": -22.92030558761905,
      "irr": -6.647606765926318,
      "terminal_pe_irr": 2.687632557481079,
      "verdict": "WATCHLIST",
      "business_score_synt": 87.28496376811596,
      "investor_score_synt": 65.29403051774375,
      "market_score_synt": 64.2,
      "verdict_synt": "WATCHLIST",
      "confidence_synt": "High",
      "dps": 0.0,
      "net_debt": 5400.0,
      "pe_now": 38.35465187250181,
      "analyst_pe_fwd_3y": 23.32730726709354,
      "market_cap_m": 415611.00769042963,
      "checklist_score": 73.87159771434389,
      "checklist_final": "WATCHLIST",
      "composite": {
        "score": 26.1,
        "rating": "Weak risk/reward",
        "components": [
          {
            "key": "irr",
            "label": "IRR",
            "input": 2.69,
            "unit": "pct",
            "contribution": 5.4
          },
          {
            "key": "mos",
            "label": "MOS",
            "input": -18.65,
            "unit": "pct",
            "contribution": 0.0
          },
          {
            "key": "checklist",
            "label": "Checklist",
            "input": 73.87,
            "unit": "score",
            "contribution": 14.8
          },
          {
            "key": "quant",
            "label": "Quant",
            "input": 59.3,
            "unit": "score",
            "contribution": 5.9
          }
        ]
      },
      "market_valuation": {
        "score": 64.2,
        "rating": "OK",
        "signals": [
          {
            "key": "expectations_gap_pp",
            "label": "Expectations gap",
            "status": "GOOD",
            "value": -11.99,
            "unit": "pct",
            "message": "Current price reflects growth expectations well below analyst forecasts."
          },
          {
            "key": "pe_vs_hist_ratio",
            "label": "P/E regime",
            "status": "OK",
            "value": 0.93,
            "unit": "ratio",
            "message": "Current valuation sits within the company's historical P/E range."
          },
          {
            "key": "peg_ratio",
            "label": "PEG sanity",
            "status": "OK",
            "value": 1.91,
            "unit": "ratio",
            "message": "Valuation appears broadly aligned with expected earnings growth."
          },
          {
            "key": "yield_sanity",
            "label": "FCF yield",
            "status": "OK",
            "value": 2.28,
            "unit": "pct",
            "message": "Free cash flow yield provides a modest valuation anchor."
          },
          {
            "key": "implied_irr_pct",
            "label": "Implied IRR",
            "status": "BAD",
            "value": 2.69,
            "unit": "pct",
            "message": "Current price offers very low IRR."
          }
        ]
      },
      "gqs": {
        "score": 79.4,
        "rating": "OK",
        "pillars": [
          {
            "key": "revenue",
            "label": "Revenue",
            "score": 77.7
          },
          {
            "key": "margin",
            "label": "Margin",
            "score": 83.4
          },
          {
            "key": "buybacks",
            "label": "Buybacks",
            "score": null
          },
          {
            "key": "roic",
            "label": "ROIC",
            "score": 77.0
          }
        ]
      },
      "pillar_scores": {
        "quality": 81.60703933747412,
        "profitability": 94.125,
        "capital_allocation": 89.8,
        "financial_health": 83.5
      },
      "valuation_state": "Expensive",
      "why": [
        "ROIC adj",
        "ROIC spread",
        "ROIC 5Y avg",
        "ROIC",
        "Operating margin trend 3Y"
      ],
      "risks": [
        "ROIC persistence",
        "Working capital / Revenue",
        "PEG Ratio",
        "EV / NOPAT",
        "Market Implied Growth"
      ],
      "meta": {
        "sector_mode": "TECH",
        "aim_verdict_score": 73.87159771434389,
        "confidence_score": 100.0,
        "confidence_label": "High",
        "freshness_label": "Fresh",
        "model_last_computed_at": "2026-04-07T16:35:28",
        "price_last_updated_at": "2026-04-07 16:35:25"
      }
    },
    {
      "ticker": "PLTR",
      "company": "Palantir Technologies Inc.",
      "currency": "USD",
      "sector": "TECH",
      "price": 145.90499877929688,
      "fair_value": 117.58076634109689,
      "mos": -24.089171485779033,
      "irr": -6.941644893583154,
      "terminal_pe_irr": 2.364190617058548,
      "verdict": "WATCHLIST",
      "business_score_synt": 86.22000000000001,
      "investor_score_synt": 64.70978416454895,
      "market_score_synt": 38.4,
      "verdict_synt": "WATCHLIST",
      "confidence_synt": "High",
      "dps": 0.0,
      "net_debt": -6947.66,
      "pe_now": 231.5952361576141,
      "analyst_pe_fwd_3y": 70.31922609474,
      "market_cap_m": 374246.3218688965,
      "checklist_score": 68.0519136658196,
      "checklist_final": "WATCHLIST",
      "composite": {
        "score": 24.8,
        "rating": "Weak risk/reward",
        "components": [
          {
            "key": "irr",
            "label": "IRR",
            "input": 2.36,
            "unit": "pct",
            "contribution": 4.7
          },
          {
            "key": "mos",
            "label": "MOS",
            "input": -19.41,
            "unit": "pct",
            "contribution": 0.0
          },
          {
            "key": "checklist",
            "label": "Checklist",
            "input": 68.05,
            "unit": "score",
            "contribution": 13.6
          },
          {
            "key": "quant",
            "label": "Quant",
            "input": 64.73,
            "unit": "score",
            "contribution": 6.5
          }
        ]
      },
      "market_valuation": {
        "score": 38.4,
        "rating": "BAD",
        "signals": [
          {
            "key": "expectations_gap_pp",
            "label": "Expectations gap",
            "status": "GOOD",
            "value": -77.2,
            "unit": "pct",
            "message": "Current price reflects growth expectations well below analyst forecasts."
          },
          {
            "key": "pe_vs_hist_ratio",
            "label": "P/E regime",
            "status": "GOOD",
            "value": 0.82,
            "unit": "ratio",
            "message": "Current valuation sits below the company's historical P/E range."
          },
          {
            "key": "peg_ratio",
            "label": "PEG sanity",
            "status": "BAD",
            "value": 3.53,
            "unit": "ratio",
            "message": "Valuation appears stretched relative to expected earnings growth."
          },
          {
            "key": "yield_sanity",
            "label": "FCF yield",
            "status": "BAD",
            "value": 0.56,
            "unit": "pct",
            "message": "Free cash flow yield provides limited valuation support."
          },
          {
            "key": "implied_irr_pct",
            "label": "Implied IRR",
            "status": "BAD",
            "value": 2.36,
            "unit": "pct",
            "message": "Current price offers very low IRR."
          }
        ]
      },
      "gqs": {
        "score": 65.9,
        "rating": "WARNING",
        "pillars": [
          {
            "key": "revenue",
            "label": "Revenue",
            "score": 63.7
          },
          {
            "key": "margin",
            "label": "Margin",
            "score": 33.3
          },
          {
            "key": "buybacks",
            "label": "Buybacks",
            "score": 100.0
          },
          {
            "key": "roic",
            "label": "ROIC",
            "score": 66.7
          }
        ]
      },
      "pillar_scores": {
        "quality": 75.86428571428571,
        "profitability": 91.25,
        "capital_allocation": 88.9,
        "financial_health": 96.75
      },
      "valuation_state": "Expensive",
      "why": [
        "Revenue CAGR",
        "ROIC adj",
        "ROIC spread",
        "Gross margin",
        "ROIC"
      ],
      "risks": [
        "Revenue volatility",
        "Operating margin stability",
        "Revenue/EBIT divergence",
        "Operating margin stability 5Y",
        "Reinvestment rate"
      ],
      "meta": {
        "sector_mode": "TECH",
        "aim_verdict_score": 68.0519136658196,
        "confidence_score": 100.0,
        "confidence_label": "High",
        "freshness_label": "Fresh",
        "model_last_computed_at": "2026-04-07T16:36:07",
        "price_last_updated_at": "2026-04-07 16:35:25"
      }
    },
    {
      "ticker": "WMT",
      "company": "Walmart Inc.",
      "currency": "USD",
      "sector": "RETAIL",
      "price": 123.9499969482422,
      "fair_value": 83.92186326070622,
      "mos": -47.69690773331281,
      "irr": -12.190224715734654,
      "terminal_pe_irr": -3.4092471873081065,
      "verdict": "SPECULATIVE",
      "business_score_synt": 76.54932294797302,
      "investor_score_synt": 60.55824305972973,
      "market_score_synt": 23.0,
      "verdict_synt": "SPECULATIVE",
      "confidence_synt": "High",
      "dps": null,
      "net_debt": 56368.0,
      "pe_now": 45.23722516359204,
      "analyst_pe_fwd_3y": 29.01673491998467,
      "market_cap_m": 991599.9755859376,
      "checklist_score": 59.443026403081106,
      "checklist_final": "SPECULATIVE",
      "composite": {
        "score": 15.8,
        "rating": "Weak risk/reward",
        "components": [
          {
            "key": "irr",
            "label": "IRR",
            "input": -3.41,
            "unit": "pct",
            "contribution": 0.0
          },
          {
            "key": "mos",
            "label": "MOS",
            "input": -32.29,
            "unit": "pct",
            "contribution": 0.0
          },
          {
            "key": "checklist",
            "label": "Checklist",
            "input": 59.44,
            "unit": "score",
            "contribution": 11.9
          },
          {
            "key": "quant",
            "label": "Quant",
            "input": 39.2,
            "unit": "score",
            "contribution": 3.9
          }
        ]
      },
      "market_valuation": {
        "score": 23.0,
        "rating": "BAD",
        "signals": [
          {
            "key": "expectations_gap_pp",
            "label": "Expectations gap",
            "status": "BAD",
            "value": 10.14,
            "unit": "pct",
            "message": "Current price reflects growth expectations above analyst forecasts."
          },
          {
            "key": "pe_vs_hist_ratio",
            "label": "P/E regime",
            "status": "WARNING",
            "value": 1.32,
            "unit": "ratio",
            "message": "Current valuation sits above the company's historical P/E range."
          },
          {
            "key": "peg_ratio",
            "label": "PEG sanity",
            "status": "BAD",
            "value": 4.17,
            "unit": "ratio",
            "message": "Valuation appears stretched relative to expected earnings growth."
          },
          {
            "key": "yield_sanity",
            "label": "FCF yield",
            "status": "WARNING",
            "value": 1.5,
            "unit": "pct",
            "message": "Free cash flow yield provides limited valuation support."
          },
          {
            "key": "implied_irr_pct",
            "label": "Implied IRR",
            "status": "BAD",
            "value": -3.41,
            "unit": "pct",
            "message": "Current price implies negative IRR."
          }
        ]
      },
      "gqs": {
        "score": 56.3,
        "rating": "WEAK",
        "pillars": [
          {
            "key": "revenue",
            "label": "Revenue",
            "score": 64.1
          },
          {
            "key": "margin",
            "label": "Margin",
            "score": 49.0
          },
          {
            "key": "buybacks",
            "label": "Buybacks",
            "score": null
          },
          {
            "key": "roic",
            "label": "ROIC",
            "score": 55.9
          }
        ]
      },
      "pillar_scores": {
        "quality": 79.40052093768784,
        "profitability": 69.0,
        "capital_allocation": 83.9,
        "financial_health": 72.52083333333333
      },
      "valuation_state": "Expensive",
      "why": [
        "Revenue CAGR",
        "ROIC adj",
        "ROIC 5Y avg",
        "Operating margin stability 5Y",
        "ROIC"
      ],
      "risks": [
        "EBIT CAGR",
        "Operating margin",
        "Gross margin",
        "NOPAT margin",
        "Cash ratio"
      ],
      "meta": {
        "sector_mode": "RETAIL",
        "aim_verdict_score": 59.443026403081106,
        "confidence_score": 100.0,
        "confidence_label": "High",
        "freshness_label": "Fresh",
        "model_last_computed_at": "2026-04-07T16:35:49",
        "price_last_updated_at": "2026-04-07 16:35:25"
      }
    },
    {
      "ticker": "ORCL",
      "company": "Oracle Corporation",
      "currency": "USD",
      "sector": "TECH",
      "price": 142.0800018310547,
      "fair_value": 178.24943651389924,
      "mos": 20.291472102367177,
      "irr": 7.852877670681946,
      "terminal_pe_irr": 18.638165437750164,
      "verdict": "WATCHLIST",
      "business_score_synt": 63.022971014492754,
      "investor_score_synt": 76.0295000154967,
      "market_score_synt": 83.4,
      "verdict_synt": "WATCHLIST",
      "confidence_synt": "High",
      "dps": 1.7,
      "net_debt": 114133.0,
      "pe_now": 25.508079323349136,
      "analyst_pe_fwd_3y": 23.92451631963495,
      "market_cap_m": 407201.28524780273,
      "checklist_score": 72.30098841199579,
      "checklist_final": "WATCHLIST",
      "composite": {
        "score": 90.9,
        "rating": "Strong opportunity",
        "components": [
          {
            "key": "irr",
            "label": "IRR",
            "input": 18.64,
            "unit": "pct",
            "contribution": 37.3
          },
          {
            "key": "mos",
            "label": "MOS",
            "input": 25.46,
            "unit": "pct",
            "contribution": 30.0
          },
          {
            "key": "checklist",
            "label": "Checklist",
            "input": 72.3,
            "unit": "score",
            "contribution": 14.5
          },
          {
            "key": "quant",
            "label": "Quant",
            "input": 91.2,
            "unit": "score",
            "contribution": 9.1
          }
        ]
      },
      "market_valuation": {
        "score": 83.4,
        "rating": "GOOD",
        "signals": [
          {
            "key": "expectations_gap_pp",
            "label": "Expectations gap",
            "status": "GOOD",
            "value": -25.22,
            "unit": "pct",
            "message": "Current price reflects growth expectations well below analyst forecasts."
          },
          {
            "key": "pe_vs_hist_ratio",
            "label": "P/E regime",
            "status": "OK",
            "value": 1.06,
            "unit": "ratio",
            "message": "Current valuation sits within the company's historical P/E range."
          },
          {
            "key": "peg_ratio",
            "label": "PEG sanity",
            "status": "GOOD",
            "value": 1.0,
            "unit": "ratio",
            "message": "Valuation appears attractive relative to expected earnings growth."
          },
          {
            "key": "yield_sanity",
            "label": "Earnings yield",
            "status": "OK",
            "value": 3.06,
            "unit": "pct",
            "message": "Earnings yield provides a modest valuation anchor."
          },
          {
            "key": "implied_irr_pct",
            "label": "Implied IRR",
            "status": "GOOD",
            "value": 18.64,
            "unit": "pct",
            "message": "Current price offers very attractive IRR."
          }
        ]
      },
      "gqs": {
        "score": 54.9,
        "rating": "WEAK",
        "pillars": [
          {
            "key": "revenue",
            "label": "Revenue",
            "score": 72.8
          },
          {
            "key": "margin",
            "label": "Margin",
            "score": 54.1
          },
          {
            "key": "buybacks",
            "label": "Buybacks",
            "score": 36.8
          },
          {
            "key": "roic",
            "label": "ROIC",
            "score": 55.7
          }
        ]
      },
      "pillar_scores": {
        "quality": 76.23229813664595,
        "profitability": 69.0,
        "capital_allocation": 44.458333333333336,
        "financial_health": 45.0
      },
      "valuation_state": "Attractive",
      "why": [
        "Gross margin",
        "Operating margin",
        "ROIC 5Y avg",
        "Operating margin stability 5Y",
        "R&D / Revenue"
      ],
      "risks": [
        "Operating margin trend 3Y",
        "Incremental ROIC",
        "ROIC spread",
        "Growth efficiency",
        "CAPEX / Revenue"
      ],
      "meta": {
        "sector_mode": "TECH",
        "aim_verdict_score": 72.30098841199579,
        "confidence_score": 100.0,
        "confidence_label": "High",
        "freshness_label": "Fresh",
        "model_last_computed_at": "2026-04-07T16:35:59",
        "price_last_updated_at": "2026-04-07 16:35:25"
      }
    },
    {
      "ticker": "C",
      "company": "Citigroup Inc.",
      "currency": "USD",
      "sector": "FINANCIAL",
      "price": 116.78500366210938,
      "fair_value": 94.4402704733283,
      "mos": -23.660174919862868,
      "irr": -6.8341577453942755,
      "terminal_pe_irr": 2.482426480066313,
      "verdict": "SPECULATIVE",
      "business_score_synt": 65.50087578369906,
      "investor_score_synt": 58.420430499177556,
      "market_score_synt": 39.4,
      "verdict_synt": "SPECULATIVE",
      "confidence_synt": "High",
      "dps": 2.32,
      "net_debt": -33752.0,
      "pe_now": 16.707439722762427,
      "analyst_pe_fwd_3y": 8.989726240479664,
      "market_cap_m": 218738.31185913086,
      "checklist_score": 50.44852251315065,
      "checklist_final": "SPECULATIVE",
      "composite": {
        "score": 21.6,
        "rating": "Weak risk/reward",
        "components": [
          {
            "key": "irr",
            "label": "IRR",
            "input": 2.48,
            "unit": "pct",
            "contribution": 5.0
          },
          {
            "key": "mos",
            "label": "MOS",
            "input": -19.13,
            "unit": "pct",
            "contribution": 0.0
          },
          {
            "key": "checklist",
            "label": "Checklist",
            "input": 50.45,
            "unit": "score",
            "contribution": 10.1
          },
          {
            "key": "quant",
            "label": "Quant",
            "input": 64.96,
            "unit": "score",
            "contribution": 6.5
          }
        ]
      },
      "market_valuation": {
        "score": 39.4,
        "rating": "BAD",
        "signals": [
          {
            "key": "expectations_gap_pp",
            "label": "Expectations gap",
            "status": "BAD",
            "value": 8.43,
            "unit": "pct",
            "message": "Current price reflects growth expectations above analyst forecasts."
          },
          {
            "key": "pe_vs_hist_ratio",
            "label": "P/E regime",
            "status": "WARNING",
            "value": 1.29,
            "unit": "ratio",
            "message": "Current valuation sits above the company's historical P/E range."
          },
          {
            "key": "peg_ratio",
            "label": "PEG sanity",
            "status": "N/A",
            "value": null,
            "unit": "ratio",
            "message": "Not applicable for FINANCE sector."
          },
          {
            "key": "yield_sanity",
            "label": "Earnings yield",
            "status": "GOOD",
            "value": 6.54,
            "unit": "pct",
            "message": "Earnings yield provides a strong valuation anchor."
          },
          {
            "key": "implied_irr_pct",
            "label": "Implied IRR",
            "status": "BAD",
            "value": 2.48,
            "unit": "pct",
            "message": "Current price offers very low IRR."
          }
        ]
      },
      "gqs": {
        "score": 58.6,
        "rating": "WEAK",
        "pillars": [
          {
            "key": "revenue",
            "label": "Revenue",
            "score": 60.9
          },
          {
            "key": "margin",
            "label": "Margin",
            "score": 100.0
          },
          {
            "key": "buybacks",
            "label": "Buybacks",
            "score": 27.8
          },
          {
            "key": "roic",
            "label": "ROIC",
            "score": 45.9
          }
        ]
      },
      "pillar_scores": {
        "quality": 80.53350313479623,
        "profitability": 49.0,
        "capital_allocation": 52.699999999999996,
        "financial_health": 75.875
      },
      "valuation_state": "Expensive",
      "why": [
        "Capital Buffer",
        "NPL Ratio",
        "CET1 Ratio",
        "NIM to NPL",
        "CET1 to NPL"
      ],
      "risks": [
        "Deposits / Loans Trend 3Y",
        "Deposit vs Loan Growth Spread 3Y",
        "NPL Trend 3Y",
        "ROE",
        "NIM"
      ],
      "meta": {
        "sector_mode": "FINANCIAL",
        "aim_verdict_score": 50.44852251315065,
        "confidence_score": 100.0,
        "confidence_label": "High",
        "freshness_label": "Fresh",
        "model_last_computed_at": "2026-04-07T16:36:19",
        "price_last_updated_at": "2026-04-07 16:35:25"
      }
    }
  ]
}